pyrulo_qt/__init__.py
pyrulo_qt/algorithms_selector.py
pyrulo_qt/algorithms_selector.ui
pyrulo_qt/selector_setting_drawer.py
pyrulo_qt/selector_setting_type.py
pyrulo_qt/ui_configurable_selector.py
pyrulo_qt-0.3.6.dist-info/LICENSE
pyrulo_qt-0.3.6.dist-info/METADATA
pyrulo_qt-0.3.6.dist-info/WHEEL
pyrulo_qt-0.3.6.dist-info/top_level.txt
pyrulo_qt-0.3.6.dist-info/RECORD
